chromstream/__init__.py
chromstream/data_processing.py
chromstream/objects.py
chromstream/parsers.py
chromstream/py.typed
chromstream/__pycache__/__init__.cpython-310.pyc
chromstream/__pycache__/__init__.cpython-311.pyc
chromstream/__pycache__/data_processing.cpython-310.pyc
chromstream/__pycache__/data_processing.cpython-311.pyc
chromstream/__pycache__/objects.cpython-310.pyc
chromstream/__pycache__/objects.cpython-311.pyc
chromstream/__pycache__/parsers.cpython-310.pyc
chromstream/__pycache__/parsers.cpython-311.pyc
chromstream-0.0.2.dist-info/licenses/LICENSE.md
chromstream-0.0.2.dist-info/METADATA
chromstream-0.0.2.dist-info/WHEEL
chromstream-0.0.2.dist-info/top_level.txt
chromstream-0.0.2.dist-info/RECORD
