Metadata-Version: 2.4
Name: chromstream
Version: 0.0.2
Summary: A Python package for online gas chromatography.
Author-email: Sebastian Rejman <s.rejman@uu.nl>
License: MIT
Project-URL: repository, https://github.com/Quantum-Accelerators/chromstream
Project-URL: documentation, https://quantum-accelerators.github.io/chromstream/
Project-URL: changelog, https://github.com/Quantum-Accelerators/chromstream/blob/main/CHANGELOG.md
Keywords: GC
Classifier: Development Status :: 4 - Beta
Classifier: Intended Audience :: Science/Research
Classifier: Programming Language :: Python :: 3
Classifier: Programming Language :: Python :: 3.10
Classifier: Programming Language :: Python :: 3.11
Classifier: Programming Language :: Python :: 3.12
Classifier: Programming Language :: Python :: 3.13
Classifier: Intended Audience :: Science/Research
Classifier: Topic :: Scientific/Engineering
Classifier: Operating System :: Microsoft :: Windows
Classifier: Operating System :: Unix
Classifier: Operating System :: MacOS
Requires-Python: >=3.9
License-File: LICENSE.md
Requires-Dist: matplotlib>=3.9.4
Requires-Dist: numpy
Requires-Dist: pandas>=2.2.2
Requires-Dist: scipy>=1.13.1
Provides-Extra: dev
Requires-Dist: pytest>=7.4.0; extra == "dev"
Requires-Dist: pytest-cov>=3.0.0; extra == "dev"
Requires-Dist: ruff>=0.0.285; extra == "dev"
Provides-Extra: docs
Requires-Dist: mkdocs>=1.6.1; extra == "docs"
Requires-Dist: ipympl>=0.9.7; extra == "docs"
Requires-Dist: ipykernel>=6.30.1; extra == "docs"
Requires-Dist: mkdocs-autorefs>=1.4.3; extra == "docs"
Requires-Dist: mkdocs-gen-files>=0.5.0; extra == "docs"
Requires-Dist: mkdocs-include-markdown-plugin>=7.1.7; extra == "docs"
Requires-Dist: mkdocs-jupyter>=0.25.1; extra == "docs"
Requires-Dist: mkdocs-literate-nav>=0.6.2; extra == "docs"
Requires-Dist: mkdocs-material>=9.6.19; extra == "docs"
Requires-Dist: mkdocstrings>=0.30.0; extra == "docs"
Requires-Dist: mkdocstrings-python>=1.18.2; extra == "docs"
Requires-Dist: pillow>=10.0.0; extra == "docs"
Requires-Dist: cairosvg>=2.7.1; extra == "docs"
Dynamic: license-file
